{ "height":9,
 "layers":[
        {
         "draworder":"topdown",
         "name":"obj",
         "objects":[
                {
                 "gid":44,
                 "height":280,
                 "id":1,
                 "name":"tree_2_1",
                 "properties":
                    {
                     "height":280,
                     "width":228
                    },
                 "propertytypes":
                    {
                     "height":"float",
                     "width":"float"
                    },
                 "rotation":0,
                 "type":"tree_2",
                 "visible":true,
                 "width":228,
                 "x":1366,
                 "y":794
                }, 
                {
                 "gid":43,
                 "height":504,
                 "id":4,
                 "name":"tree_1_1",
                 "properties":
                    {
                     "height":504,
                     "width":642
                    },
                 "propertytypes":
                    {
                     "height":"float",
                     "width":"float"
                    },
                 "rotation":0,
                 "type":"tree_1",
                 "visible":true,
                 "width":642,
                 "x":3187,
                 "y":513
                }, 
                {
                 "gid":46,
                 "height":210,
                 "id":5,
                 "name":"snowman1",
                 "properties":
                    {
                     "flip":true,
                     "height":210,
                     "width":193
                    },
                 "propertytypes":
                    {
                     "flip":"bool",
                     "height":"float",
                     "width":"float"
                    },
                 "rotation":0,
                 "type":"snowman",
                 "visible":true,
                 "width":193,
                 "x":6432,
                 "y":257
                }, 
                {
                 "gid":46,
                 "height":210,
                 "id":12,
                 "name":"snowman2",
                 "properties":
                    {
                     "flip":true,
                     "height":210,
                     "width":193
                    },
                 "propertytypes":
                    {
                     "flip":"bool",
                     "height":"float",
                     "width":"float"
                    },
                 "rotation":0,
                 "type":"snowman",
                 "visible":true,
                 "width":193,
                 "x":7719.5,
                 "y":1027
                }, 
                {
                 "gid":37,
                 "height":101,
                 "id":21,
                 "name":"icebox2",
                 "properties":
                    {
                     "height":101,
                     "width":101
                    },
                 "propertytypes":
                    {
                     "height":"float",
                     "width":"float"
                    },
                 "rotation":0,
                 "type":"icebox",
                 "visible":true,
                 "width":101,
                 "x":10486,
                 "y":1058
                }, 
                {
                 "gid":40,
                 "height":131.483,
                 "id":22,
                 "name":"sign_2_1",
                 "properties":
                    {
                     "height":131.48,
                     "width":123
                    },
                 "propertytypes":
                    {
                     "height":"float",
                     "width":"float"
                    },
                 "rotation":0,
                 "type":"sign_2",
                 "visible":true,
                 "width":123,
                 "x":10485,
                 "y":394
                }, 
                {
                 "gid":37,
                 "height":101,
                 "id":25,
                 "name":"icebox2",
                 "properties":
                    {
                     "height":101,
                     "width":101
                    },
                 "propertytypes":
                    {
                     "height":"float",
                     "width":"float"
                    },
                 "rotation":0,
                 "type":"icebox",
                 "visible":true,
                 "width":101,
                 "x":10486,
                 "y":1058
                }, 
                {
                 "gid":37,
                 "height":101,
                 "id":26,
                 "name":"icebox3",
                 "properties":
                    {
                     "height":101,
                     "width":101
                    },
                 "propertytypes":
                    {
                     "height":"float",
                     "width":"float"
                    },
                 "rotation":0,
                 "type":"icebox",
                 "visible":true,
                 "width":101,
                 "x":15335.1,
                 "y":1075.44
                }, 
                {
                 "gid":37,
                 "height":101,
                 "id":27,
                 "name":"icebox4",
                 "properties":
                    {
                     "height":101,
                     "width":101
                    },
                 "propertytypes":
                    {
                     "height":"float",
                     "width":"float"
                    },
                 "rotation":0,
                 "type":"icebox",
                 "visible":true,
                 "width":101,
                 "x":21461.6,
                 "y":1076.77
                }, 
                {
                 "gid":37,
                 "height":101,
                 "id":28,
                 "name":"icebox5",
                 "properties":
                    {
                     "height":101,
                     "width":101
                    },
                 "propertytypes":
                    {
                     "height":"float",
                     "width":"float"
                    },
                 "rotation":0,
                 "type":"icebox",
                 "visible":true,
                 "width":101,
                 "x":22095,
                 "y":1082.83
                }, 
                {
                 "gid":37,
                 "height":101,
                 "id":29,
                 "name":"icebox6",
                 "properties":
                    {
                     "height":101,
                     "width":101
                    },
                 "propertytypes":
                    {
                     "height":"float",
                     "width":"float"
                    },
                 "rotation":0,
                 "type":"icebox",
                 "visible":true,
                 "width":101,
                 "x":23116.2,
                 "y":1082.83
                }, 
                {
                 "gid":43,
                 "height":249.455,
                 "id":37,
                 "name":"tree_1_3",
                 "properties":
                    {
                     "height":249.46,
                     "width":317.76
                    },
                 "propertytypes":
                    {
                     "height":"float",
                     "width":"float"
                    },
                 "rotation":0,
                 "type":"tree_1",
                 "visible":true,
                 "width":317.758,
                 "x":15905.4,
                 "y":655
                }, 
                {
                 "gid":37,
                 "height":128,
                 "id":40,
                 "name":"icebox3",
                 "properties":
                    {
                     "flip":false,
                     "height":128,
                     "width":1150.67
                    },
                 "propertytypes":
                    {
                     "flip":"bool",
                     "height":"float",
                     "width":"float"
                    },
                 "rotation":0,
                 "type":"icebox",
                 "visible":true,
                 "width":1150.67,
                 "x":33025.2,
                 "y":899
                }, 
                {
                 "gid":38,
                 "height":201,
                 "id":49,
                 "name":"igloo2",
                 "properties":
                    {
                     "height":201,
                     "width":511
                    },
                 "propertytypes":
                    {
                     "height":"float",
                     "width":"float"
                    },
                 "rotation":0,
                 "type":"igloo",
                 "visible":true,
                 "width":511,
                 "x":9206.5,
                 "y":1033.5
                }, 
                {
                 "gid":47,
                 "height":116.465,
                 "id":50,
                 "name":"stone2",
                 "properties":
                    {
                     "height":116.47,
                     "width":185.15
                    },
                 "propertytypes":
                    {
                     "height":"float",
                     "width":"float"
                    },
                 "rotation":0,
                 "type":"stone",
                 "visible":true,
                 "width":185.15,
                 "x":14871.9,
                 "y":653.268
                }],
         "offsetx":256,
         "offsety":-428,
         "opacity":1,
         "type":"objectgroup",
         "visible":false,
         "x":0,
         "y":0
        }, 
        {
         "draworder":"topdown",
         "name":"box",
         "objects":[
                {
                 "gid":48,
                 "height":70,
                 "id":41,
                 "name":"crate1",
                 "properties":
                    {
                     "height":70,
                     "width":70
                    },
                 "propertytypes":
                    {
                     "height":"float",
                     "width":"float"
                    },
                 "rotation":0,
                 "type":"crate",
                 "visible":true,
                 "width":70,
                 "x":12314.7,
                 "y":900.334
                }, 
                {
                 "gid":48,
                 "height":25,
                 "id":43,
                 "name":"crate2",
                 "properties":
                    {
                     "height":25,
                     "width":25
                    },
                 "propertytypes":
                    {
                     "height":"float",
                     "width":"float"
                    },
                 "rotation":0,
                 "type":"crate",
                 "visible":true,
                 "width":25,
                 "x":16237.4,
                 "y":643.409
                }, 
                {
                 "gid":48,
                 "height":50,
                 "id":44,
                 "name":"crate3",
                 "properties":
                    {
                     "height":50,
                     "width":50
                    },
                 "propertytypes":
                    {
                     "height":"float",
                     "width":"float"
                    },
                 "rotation":0,
                 "type":"crate",
                 "visible":true,
                 "width":50,
                 "x":17132.3,
                 "y":772.591
                }, 
                {
                 "gid":48,
                 "height":165,
                 "id":45,
                 "name":"crate4",
                 "properties":
                    {
                     "height":165,
                     "width":165
                    },
                 "propertytypes":
                    {
                     "height":"float",
                     "width":"float"
                    },
                 "rotation":0,
                 "type":"crate",
                 "visible":true,
                 "width":165,
                 "x":22705.3,
                 "y":1155.59
                }, 
                {
                 "gid":48,
                 "height":127,
                 "id":46,
                 "name":"crate6",
                 "properties":
                    {
                     "height":127,
                     "width":127
                    },
                 "propertytypes":
                    {
                     "height":"float",
                     "width":"float"
                    },
                 "rotation":0,
                 "type":"crate",
                 "visible":true,
                 "width":127,
                 "x":36487,
                 "y":1027.67
                }, 
                {
                 "gid":48,
                 "height":639.727,
                 "id":47,
                 "name":"crate5",
                 "properties":
                    {
                     "height":639.73,
                     "width":4479
                    },
                 "propertytypes":
                    {
                     "height":"float",
                     "width":"float"
                    },
                 "rotation":0,
                 "type":"crate",
                 "visible":true,
                 "width":4479,
                 "x":25855,
                 "y":644.394
                }, 
                {
                 "gid":48,
                 "height":50,
                 "id":48,
                 "name":"crate7",
                 "properties":
                    {
                     "height":50,
                     "width":50
                    },
                 "propertytypes":
                    {
                     "height":"float",
                     "width":"float"
                    },
                 "rotation":0,
                 "type":"crate",
                 "visible":true,
                 "width":50,
                 "x":37839.3,
                 "y":900.379
                }, 
                {
                 "gid":48,
                 "height":70,
                 "id":59,
                 "name":"crate8",
                 "properties":
                    {
                     "height":70,
                     "width":70
                    },
                 "propertytypes":
                    {
                     "height":"float",
                     "width":"float"
                    },
                 "rotation":0,
                 "type":"crate",
                 "visible":true,
                 "width":70,
                 "x":4012.88,
                 "y":869.909
                }, 
                {
                 "gid":48,
                 "height":110,
                 "id":60,
                 "name":"crate9",
                 "properties":
                    {
                     "height":110,
                     "width":110
                    },
                 "propertytypes":
                    {
                     "height":"float",
                     "width":"float"
                    },
                 "rotation":0,
                 "type":"crate",
                 "visible":true,
                 "width":110,
                 "x":7932.03,
                 "y":1029.18
                }, 
                {
                 "gid":48,
                 "height":100,
                 "id":62,
                 "name":"crate10",
                 "properties":
                    {
                     "height":100,
                     "width":100
                    },
                 "propertytypes":
                    {
                     "height":"float",
                     "width":"float"
                    },
                 "rotation":0,
                 "type":"crate",
                 "visible":true,
                 "width":100,
                 "x":31633.7,
                 "y":777.003
                }, 
                {
                 "gid":48,
                 "height":100,
                 "id":67,
                 "name":"crate11",
                 "properties":
                    {
                     "height":100,
                     "width":100
                    },
                 "propertytypes":
                    {
                     "height":"float",
                     "width":"float"
                    },
                 "rotation":0,
                 "type":"crate",
                 "visible":true,
                 "width":100,
                 "x":31903,
                 "y":771.67
                }, 
                {
                 "gid":48,
                 "height":100,
                 "id":70,
                 "name":"crate12",
                 "properties":
                    {
                     "height":100,
                     "width":100
                    },
                 "propertytypes":
                    {
                     "height":"float",
                     "width":"float"
                    },
                 "rotation":0,
                 "type":"crate",
                 "visible":true,
                 "width":100,
                 "x":32183,
                 "y":773.003
                }, 
                {
                 "gid":48,
                 "height":100,
                 "id":72,
                 "name":"crate13",
                 "properties":
                    {
                     "height":100,
                     "width":100
                    },
                 "propertytypes":
                    {
                     "height":"float",
                     "width":"float"
                    },
                 "rotation":0,
                 "type":"crate",
                 "visible":true,
                 "width":100,
                 "x":32456.3,
                 "y":771.67
                }, 
                {
                 "gid":48,
                 "height":127,
                 "id":77,
                 "name":"crate14",
                 "properties":
                    {
                     "height":127,
                     "width":127
                    },
                 "propertytypes":
                    {
                     "height":"float",
                     "width":"float"
                    },
                 "rotation":0,
                 "type":"crate",
                 "visible":true,
                 "width":127,
                 "x":36229.4,
                 "y":379.185
                }],
         "offsetx":248,
         "offsety":-428,
         "opacity":1,
         "type":"objectgroup",
         "visible":false,
         "x":0,
         "y":0
        }, 
        {
         "draworder":"topdown",
         "name":"trap",
         "objects":[
                {
                 "gid":49,
                 "height":78,
                 "id":52,
                 "name":"crystal1",
                 "properties":
                    {
                     "height":78,
                     "width":97
                    },
                 "propertytypes":
                    {
                     "height":"float",
                     "width":"float"
                    },
                 "rotation":0,
                 "type":"crystal",
                 "visible":true,
                 "width":97,
                 "x":5770,
                 "y":643
                }, 
                {
                 "gid":49,
                 "height":78,
                 "id":54,
                 "name":"crystal2",
                 "properties":
                    {
                     "height":78,
                     "width":97
                    },
                 "propertytypes":
                    {
                     "height":"float",
                     "width":"float"
                    },
                 "rotation":0,
                 "type":"crystal",
                 "visible":true,
                 "width":97,
                 "x":9245.33,
                 "y":1034.33
                }, 
                {
                 "gid":49,
                 "height":78,
                 "id":55,
                 "name":"crystal3",
                 "properties":
                    {
                     "height":78,
                     "width":97
                    },
                 "propertytypes":
                    {
                     "height":"float",
                     "width":"float"
                    },
                 "rotation":0,
                 "type":"crystal",
                 "visible":true,
                 "width":97,
                 "x":12059,
                 "y":901.333
                }, 
                {
                 "gid":49,
                 "height":78,
                 "id":56,
                 "name":"crystal4",
                 "properties":
                    {
                     "height":78,
                     "width":97
                    },
                 "propertytypes":
                    {
                     "height":"float",
                     "width":"float"
                    },
                 "rotation":0,
                 "type":"crystal",
                 "visible":true,
                 "width":97,
                 "x":15421,
                 "y":517.424
                }, 
                {
                 "gid":49,
                 "height":94,
                 "id":57,
                 "name":"crystal5",
                 "properties":
                    {
                     "height":78,
                     "width":97
                    },
                 "propertytypes":
                    {
                     "height":"float",
                     "width":"float"
                    },
                 "rotation":0,
                 "type":"crystal",
                 "visible":true,
                 "width":116.897,
                 "x":18949.8,
                 "y":646.091
                }, 
                {
                 "gid":49,
                 "height":216,
                 "id":58,
                 "name":"crystal4",
                 "properties":
                    {
                     "height":216,
                     "width":268.62
                    },
                 "propertytypes":
                    {
                     "height":"float",
                     "width":"float"
                    },
                 "rotation":0,
                 "type":"crystal",
                 "visible":true,
                 "width":268.615,
                 "x":28866.1,
                 "y":1032.09
                }, 
                {
                 "gid":49,
                 "height":94,
                 "id":61,
                 "name":"crystal6",
                 "properties":
                    {
                     "height":78,
                     "width":97
                    },
                 "propertytypes":
                    {
                     "height":"float",
                     "width":"float"
                    },
                 "rotation":0,
                 "type":"crystal",
                 "visible":true,
                 "width":116.897,
                 "x":31492.7,
                 "y":778.212
                }, 
                {
                 "gid":49,
                 "height":94,
                 "id":68,
                 "name":"crystal7",
                 "properties":
                    {
                     "height":78,
                     "width":97
                    },
                 "propertytypes":
                    {
                     "height":"float",
                     "width":"float"
                    },
                 "rotation":0,
                 "type":"crystal",
                 "visible":true,
                 "width":116.897,
                 "x":31762.1,
                 "y":772.879
                }, 
                {
                 "gid":49,
                 "height":94,
                 "id":69,
                 "name":"crystal9",
                 "properties":
                    {
                     "height":78,
                     "width":97
                    },
                 "propertytypes":
                    {
                     "height":"float",
                     "width":"float"
                    },
                 "rotation":0,
                 "type":"crystal",
                 "visible":true,
                 "width":116.897,
                 "x":32315.4,
                 "y":772.879
                }, 
                {
                 "gid":49,
                 "height":94,
                 "id":71,
                 "name":"crystal8",
                 "properties":
                    {
                     "height":78,
                     "width":97
                    },
                 "propertytypes":
                    {
                     "height":"float",
                     "width":"float"
                    },
                 "rotation":0,
                 "type":"crystal",
                 "visible":true,
                 "width":116.897,
                 "x":32042.1,
                 "y":774.212
                }, 
                {
                 "gid":49,
                 "height":94,
                 "id":73,
                 "name":"crystal10",
                 "properties":
                    {
                     "height":78,
                     "width":97
                    },
                 "propertytypes":
                    {
                     "height":"float",
                     "width":"float"
                    },
                 "rotation":0,
                 "type":"crystal",
                 "visible":true,
                 "width":116.897,
                 "x":32599.4,
                 "y":771.879
                }],
         "offsetx":244,
         "offsety":-428,
         "opacity":1,
         "type":"objectgroup",
         "visible":false,
         "x":0,
         "y":0
        }, 
        {
         "data":[0, 0, 0, 0, 0, 0, 0, 0, 0, 0, 0, 0, 0, 0, 0, 0, 0, 0, 0, 0, 0, 0, 0, 0, 0, 0, 0, 0, 0, 0, 0, 0, 0, 0, 0, 0, 0, 0, 0, 0, 0, 0, 0, 0, 0, 0, 0, 0, 0, 0, 0, 0, 0, 0, 0, 0, 0, 0, 0, 4, 4, 4, 4, 4, 0, 0, 0, 0, 0, 0, 0, 0, 0, 0, 0, 0, 0, 0, 0, 0, 0, 0, 0, 0, 0, 0, 0, 0, 0, 0, 0, 0, 0, 0, 0, 0, 0, 0, 0, 0, 0, 0, 0, 0, 0, 0, 0, 0, 0, 0, 0, 0, 0, 0, 0, 0, 0, 0, 0, 0, 0, 0, 0, 4, 4, 4, 4, 4, 0, 0, 0, 0, 0, 0, 0, 0, 0, 0, 0, 0, 0, 0, 0, 0, 0, 0, 0, 0, 0, 0, 0, 0, 0, 0, 0, 0, 2, 4, 4, 4, 4, 4, 4, 4, 4, 4, 4, 4, 4, 4, 4, 4, 4, 4, 4, 4, 4, 4, 4, 4, 4, 4, 4, 4, 5, 0, 0, 0, 0, 0, 0, 0, 0, 0, 0, 0, 0, 0, 0, 0, 0, 0, 4, 4, 0, 0, 0, 4, 0, 0, 4, 4, 4, 0, 0, 0, 4, 0, 0, 0, 4, 4, 4, 0, 4, 0, 0, 0, 4, 0, 4, 4, 4, 0, 4, 0, 0, 0, 0, 0, 0, 0, 0, 0, 0, 0, 0, 0, 0, 0, 0, 0, 0, 0, 0, 0, 0, 0, 0, 0, 0, 0, 0, 0, 0, 0, 0, 0, 0, 0, 0, 0, 0, 0, 0, 0, 0, 0, 0, 0, 0, 0, 0, 0, 0, 0, 4, 3221225481, 3221225481, 3221225481, 3221225481, 3221225481, 3221225481, 3221225481, 3221225481, 3221225481, 3221225481, 3221225481, 3221225481, 1073741825, 0, 0, 0, 0, 0, 0, 0, 0, 0, 0, 0, 0, 0, 0, 0, 0, 0, 0, 0, 0, 0, 0, 0, 0, 0, 0, 0, 0, 0, 0, 0, 0, 0, 0, 0, 0, 0, 0, 0, 0, 0, 0, 0, 0, 0, 0, 0, 0, 0, 0, 0, 0, 0, 0, 0, 0, 0, 0, 0, 4, 3221225479, 3221225481, 3221225483, 4, 0, 0, 0, 0, 0, 0, 0, 0, 0, 0, 0, 0, 0, 0, 0, 0, 0, 0, 0, 0, 0, 0, 0, 0, 0, 0, 0, 0, 0, 0, 0, 0, 0, 0, 0, 0, 0, 0, 0, 0, 0, 0, 0, 0, 0, 0, 0, 0, 0, 0, 0, 0, 0, 0, 0, 0, 0, 0, 0, 4, 4, 4, 4, 4, 0, 0, 0, 0, 0, 0, 0, 0, 0, 0, 0, 0, 0, 0, 0, 0, 0, 0, 0, 0, 0, 0, 0, 0, 0, 0, 0, 0, 3221225473, 4, 4, 4, 4, 4, 4, 4, 4, 4, 4, 4, 4, 4, 4, 4, 4, 4, 4, 4, 4, 4, 4, 4, 4, 4, 4, 4, 5, 0, 0, 0, 0, 0, 0, 0, 0, 0, 0, 0, 0, 0, 0, 0, 0, 0, 4, 0, 4, 0, 4, 0, 4, 0, 0, 4, 0, 0, 0, 0, 4, 0, 0, 0, 4, 0, 0, 0, 4, 0, 0, 0, 4, 0, 4, 0, 0, 0, 4, 0, 0, 0, 0, 0, 0, 0, 0, 0, 0, 0, 0, 0, 0, 0, 0, 0, 0, 0, 0, 0, 0, 0, 0, 0, 0, 0, 0, 0, 0, 0, 0, 0, 0, 0, 0, 0, 0, 0, 0, 0, 0, 0, 0, 0, 0, 0, 0, 0, 0, 0, 2684354569, 0, 0, 0, 0, 0, 0, 0, 0, 0, 0, 0, 0, 0, 0, 0, 0, 0, 0, 0, 0, 0, 0, 0, 0, 0, 0, 0, 0, 0, 0, 0, 0, 0, 0, 0, 0, 0, 0, 0, 0, 0, 0, 0, 0, 0, 0, 0, 0, 0, 0, 0, 0, 0, 0, 0, 0, 0, 0, 0, 0, 0, 0, 0, 17, 16, 0, 0, 0, 0, 0, 0, 0, 4, 0, 0, 0, 4, 0, 0, 0, 0, 0, 0, 0, 0, 0, 0, 0, 0, 0, 0, 0, 0, 0, 0, 0, 0, 0, 0, 0, 0, 0, 0, 0, 0, 0, 0, 0, 0, 0, 0, 0, 0, 0, 0, 0, 0, 0, 0, 0, 0, 0, 0, 0, 0, 0, 0, 0, 0, 0, 0, 0, 0, 0, 0, 0, 2147483654, 2147483654, 2147483654, 2147483654, 2147483654, 0, 0, 0, 0, 0, 0, 0, 0, 0, 0, 0, 0, 0, 0, 0, 0, 0, 0, 0, 0, 0, 0, 0, 0, 0, 0, 0, 0, 0, 3221225473, 4, 4, 4, 4, 4, 4, 4, 4, 4, 4, 4, 4, 4, 4, 4, 4, 4, 4, 4, 4, 4, 4, 4, 4, 4, 4, 5, 0, 0, 0, 0, 0, 0, 0, 0, 0, 0, 0, 0, 0, 0, 0, 0, 0, 4, 4, 0, 0, 4, 4, 4, 0, 0, 4, 0, 4, 4, 0, 4, 0, 0, 0, 4, 4, 0, 0, 0, 4, 0, 4, 0, 0, 4, 4, 0, 0, 4, 0, 0, 0, 0, 0, 0, 0, 0, 0, 0, 0, 0, 0, 0, 0, 0, 0, 0, 0, 0, 0, 0, 0, 0, 0, 0, 0, 0, 0, 0, 0, 0, 0, 0, 0, 0, 0, 0, 0, 0, 0, 0, 0, 0, 0, 0, 0, 0, 0, 0, 0, 2684354569, 0, 0, 0, 0, 0, 3221225473, 3221225481, 3221225481, 3221225481, 3221225481, 3221225481, 3221225481, 4, 0, 0, 0, 0, 0, 0, 0, 0, 0, 0, 0, 0, 0, 0, 0, 0, 0, 0, 0, 0, 0, 0, 0, 0, 0, 0, 0, 0, 0, 0, 0, 0, 0, 0, 0, 0, 0, 0, 0, 0, 0, 0, 0, 0, 0, 0, 12, 9, 0, 0, 0, 0, 0, 0, 1, 0, 0, 0, 0, 0, 0, 0, 0, 0, 0, 0, 0, 0, 0, 0, 0, 0, 0, 0, 0, 0, 0, 0, 0, 0, 0, 17, 18, 16, 0, 0, 0, 0, 0, 0, 0, 0, 0, 0, 0, 0, 0, 0, 0, 0, 0, 0, 0, 0, 0, 0, 0, 0, 0, 0, 0, 0, 0, 0, 0, 0, 0, 0, 0, 0, 0, 0, 0, 0, 0, 0, 0, 0, 0, 0, 0, 0, 0, 0, 0, 0, 0, 0, 0, 0, 0, 0, 0, 0, 0, 0, 0, 0, 0, 0, 0, 0, 0, 0, 0, 0, 0, 0, 3221225473, 4, 4, 4, 4, 4, 4, 4, 4, 4, 4, 4, 4, 4, 4, 4, 4, 4, 4, 4, 4, 4, 4, 4, 4, 4, 5, 0, 0, 0, 0, 0, 0, 0, 0, 0, 0, 0, 0, 0, 0, 0, 0, 0, 4, 0, 4, 0, 4, 0, 4, 0, 0, 4, 0, 0, 0, 0, 4, 0, 0, 0, 4, 0, 0, 0, 0, 4, 0, 4, 0, 0, 4, 0, 0, 0, 4, 0, 0, 0, 0, 0, 0, 0, 0, 0, 0, 0, 0, 0, 0, 0, 0, 0, 0, 0, 0, 0, 0, 0, 0, 0, 0, 0, 0, 0, 0, 0, 0, 0, 0, 0, 0, 0, 0, 0, 0, 0, 0, 0, 0, 0, 0, 0, 0, 0, 0, 0, 2684354569, 0, 0, 0, 0, 0, 0, 0, 0, 0, 0, 0, 0, 1610612745, 0, 0, 0, 0, 0, 0, 0, 0, 0, 0, 0, 0, 0, 0, 0, 0, 0, 17, 18, 16, 0, 0, 0, 12, 9, 9, 9, 9, 9, 9, 1, 0, 0, 0, 0, 0, 0, 0, 0, 0, 0, 0, 0, 0, 0, 0, 14, 4, 10, 10, 10, 10, 10, 10, 5, 0, 0, 0, 0, 0, 0, 0, 0, 0, 0, 0, 0, 0, 0, 0, 0, 0, 0, 0, 0, 0, 0, 0, 0, 0, 0, 0, 0, 0, 0, 0, 0, 0, 0, 0, 0, 0, 0, 0, 0, 0, 0, 0, 0, 0, 0, 0, 0, 0, 0, 0, 0, 0, 0, 0, 0, 0, 0, 0, 0, 0, 0, 0, 0, 17, 18, 16, 0, 0, 0, 0, 0, 0, 0, 0, 0, 0, 0, 0, 0, 0, 0, 0, 0, 0, 0, 0, 0, 0, 0, 0, 0, 0, 0, 0, 17, 16, 0, 17, 18, 16, 0, 0, 0, 3221225473, 1073741833, 1073741833, 1073741833, 1073741833, 1073741833, 1073741833, 1073741833, 1073741833, 1073741833, 1073741833, 1073741833, 1073741833, 1073741833, 1073741833, 1073741833, 1073741833, 1073741833, 1073741833, 1073741833, 1073741833, 1073741833, 1073741833, 1073741833, 1073741833, 3221225484, 0, 0, 0, 0, 0, 0, 0, 0, 0, 0, 0, 0, 0, 17, 16, 0, 0, 4, 4, 0, 0, 4, 0, 4, 0, 0, 4, 0, 0, 0, 0, 4, 4, 4, 0, 4, 4, 4, 0, 0, 0, 4, 0, 0, 0, 4, 4, 4, 0, 4, 4, 4, 0, 0, 0, 0, 0, 0, 0, 0, 0, 0, 0, 0, 0, 0, 0, 0, 0, 0, 0, 0, 0, 0, 0, 0, 0, 0, 0, 0, 0, 0, 0, 0, 0, 0, 0, 0, 0, 0, 0, 0, 0, 0, 0, 12, 9, 1, 0, 0, 0, 4, 9, 9, 9, 9, 9, 9, 9, 9, 1, 0, 0, 0, 1610612745, 0, 0, 0, 0, 0, 0, 0, 0, 0, 0, 0, 0, 0, 17, 18, 16, 0, 0, 0, 0, 0, 0, 12, 4, 0, 0, 2, 4, 5, 0, 0, 0, 0, 0, 0, 0, 0, 0, 0, 0, 0, 0, 0, 0, 17, 16, 0, 14, 6, 6, 6, 6, 6, 6, 15, 0, 0, 0, 0, 0, 0, 0, 4, 4, 0, 0, 0, 0, 0, 0, 0, 0, 0, 0, 0, 0, 0, 0, 17, 18, 16, 0, 0, 0, 17, 18, 16, 0, 0, 0, 0, 0, 0, 0, 0, 0, 0, 0, 0, 0, 0, 0, 0, 0, 0, 0, 0, 0, 0, 0, 0, 0, 0, 0, 0, 0, 3221225487, 3221225486, 0, 0, 0, 0, 0, 1073741830, 1073741830, 1073741830, 1073741830, 1073741830, 0, 0, 0, 0, 0, 0, 0, 0, 0, 0, 0, 0, 0, 0, 0, 0, 0, 0, 0, 17, 16, 0, 0, 0, 0, 0, 0, 0, 1, 0, 0, 0, 0, 0, 0, 0, 0, 0, 0, 0, 0, 0, 0, 0, 0, 0, 0, 0, 0, 0, 0, 0, 0, 0, 0, 0, 0, 0, 0, 0, 0, 0, 0, 0, 0, 0, 0, 17, 16, 0, 0, 0, 0, 0, 0, 0, 0, 0, 0, 0, 0, 0, 0, 0, 0, 0, 0, 0, 0, 0, 0, 0, 0, 0, 0, 0, 0, 0, 0, 0, 0, 0, 0, 0, 0, 0, 0, 0, 0, 0, 0, 0, 0, 0, 0, 0, 0, 0, 0, 0, 0, 0, 0, 0, 0, 0, 0, 0, 0, 0, 0, 0, 0, 0, 0, 0, 0, 0, 0, 0, 0, 0, 0, 0, 0, 0, 0, 0, 12, 9, 1, 0, 0, 0, 0, 0, 0, 0, 0, 0, 0, 0, 0, 0, 0, 0, 4, 4, 1, 0, 0, 1610612745, 0, 0, 0, 0, 0, 0, 0, 0, 0, 17, 18, 16, 0, 0, 0, 0, 0, 0, 17, 18, 18, 18, 4, 0, 0, 0, 2, 4, 5, 0, 0, 0, 0, 0, 0, 0, 0, 0, 0, 0, 0, 9, 0, 0, 0, 0, 0, 0, 0, 0, 0, 0, 0, 0, 0, 0, 0, 0, 0, 4, 0, 0, 0, 4, 0, 12, 9, 1, 0, 0, 0, 0, 0, 0, 0, 0, 0, 0, 0, 0, 0, 0, 0, 0, 0, 0, 0, 0, 0, 0, 0, 0, 0, 0, 0, 0, 0, 0, 0, 0, 0, 0, 0, 0, 0, 0, 0, 0, 0, 0, 0, 0, 12, 9, 1, 0, 14, 15, 0, 0, 0, 0, 0, 4, 4, 4, 4, 4, 0, 9, 0, 0, 0, 12, 1, 0, 0, 0, 0, 0, 0, 0, 0, 0, 17, 16, 0, 0, 0, 0, 0, 0, 0, 0, 0, 0, 13, 1, 0, 0, 0, 0, 0, 0, 0, 0, 0, 0, 0, 0, 0, 0, 0, 0, 0, 0, 0, 0, 0, 0, 0, 0, 0, 0, 0, 0, 0, 0, 0, 0, 0, 0, 17, 16, 0, 0, 0, 0, 0, 0, 0, 0, 0, 0, 0, 0, 0, 0, 0, 0, 0, 0, 0, 0, 0, 0, 0, 0, 0, 0, 0, 0, 0, 0, 0, 0, 0, 0, 0, 0, 0, 0, 0, 0, 0, 0, 0, 0, 0, 0, 0, 0, 0, 0, 0, 17, 18, 18, 18, 18, 18, 18, 18, 18, 18, 18, 0, 0, 12, 0, 12, 0, 12, 0, 12, 0, 12, 0, 12, 9, 9, 9, 9, 9, 1, 0, 0, 0, 0, 0, 0, 0, 0, 0, 0, 0, 0, 0, 0, 0, 0, 0, 0, 0, 0, 0, 2684354569, 0, 0, 1610612745, 0, 0, 0, 0, 0, 0, 0, 0, 0, 0, 0, 0, 0, 0, 0, 0, 0, 0, 0, 0, 0, 0, 0, 0, 0, 0, 2, 4, 5, 0, 0, 0, 0, 0, 0, 0, 0, 0, 0, 0, 0, 0, 0, 0, 0, 0, 0, 0, 0, 0, 0, 0, 0, 0, 0, 0, 0, 0, 0, 4, 0, 0, 0, 4, 0, 2, 4, 5, 0, 0, 0, 0, 0, 0, 0, 0, 12, 1, 0, 0, 0, 0, 0, 0, 0, 0, 0, 0, 17, 18, 16, 0, 17, 18, 16, 0, 9, 0, 0, 0, 0, 0, 0, 0, 0, 0, 0, 0, 0, 0, 0, 0, 0, 0, 0, 0, 0, 0, 0, 0, 0, 0, 0, 4, 4, 4, 4, 4, 0, 0, 12, 9, 1, 0, 0, 0, 0, 0, 0, 0, 17, 18, 16, 0, 0, 0, 0, 0, 0, 0, 0, 0, 0, 0, 0, 0, 4, 13, 1, 0, 0, 0, 12, 1, 0, 0, 0, 0, 0, 0, 0, 0, 0, 0, 0, 0, 0, 0, 0, 0, 0, 0, 0, 0, 0, 0, 0, 0, 0, 17, 16, 0, 0, 0, 0, 0, 0, 0, 0, 0, 0, 0, 0, 0, 0, 0, 0, 0, 0, 0, 0, 0, 0, 0, 0, 0, 0, 0, 0, 0, 0, 0, 0, 0, 0, 0, 0, 0, 0, 0, 0, 0, 0, 0, 0, 0, 0, 0, 0, 0, 0, 0, 0, 0, 0, 0, 0, 0, 0, 0, 0, 0, 0, 0, 0, 0, 0, 0, 0, 0, 0, 0, 0, 0, 0, 0, 0, 0, 0, 0, 0, 0, 0, 0, 0, 0, 0, 0, 0, 0, 0, 0, 0, 9, 0, 0, 2147483649, 9, 1, 0, 0, 9, 0, 0, 3221225473, 3221225481, 3221225481, 1073741825, 0, 1610612745, 12, 9, 9, 9, 9, 9, 9, 1, 0, 0, 0, 0, 0, 0, 0, 0, 0, 0, 0, 0, 0, 0, 0, 0, 0, 0, 14, 6, 15, 0, 0, 12, 1, 0, 12, 9, 1, 0, 0, 12, 1, 0, 0, 12, 9, 9, 9, 9, 9, 9, 9, 1, 0, 0, 0, 12, 9, 9, 7, 4, 4, 4, 4, 4, 0, 14, 6, 15, 0, 0, 12, 9, 9, 9, 9, 1, 14, 15, 0, 0, 0, 0, 0, 0, 0, 0, 0, 0, 0, 0, 0, 0, 0, 0, 0, 0, 4, 0, 0, 12, 9, 1, 0, 0, 12, 1, 0, 12, 1, 0, 12, 1, 0, 0, 0, 0, 0, 0, 0, 0, 0, 0, 0, 4, 4, 4, 4, 4, 0, 0, 0, 0, 0, 0, 0, 0, 12, 9, 1, 0, 0, 0, 0, 0, 0, 0, 0, 0, 0, 0, 0, 0, 0, 0, 0, 0, 4, 4, 13, 9, 9, 9, 8, 13, 9, 9, 1, 0, 0, 12, 9, 1, 0, 0, 12, 9, 1, 0, 0, 9, 0, 0, 12, 9, 1, 0, 2147483649, 1, 0, 0, 0, 0, 0, 0, 0, 0, 0, 0, 0, 2147483649, 9, 1, 0, 9, 0, 2147483649, 1, 0, 0, 2147483649, 9, 1, 0, 9, 0, 2147483649, 9, 1, 0, 9, 0, 2147483649, 9, 1, 0, 2147483649, 9, 1, 0, 9, 0, 9, 0, 2147483649, 9, 1, 0, 2147483649, 9, 9, 1, 9, 1, 0, 0, 0, 0, 0, 0, 0, 0, 0, 0, 0, 0, 0, 0, 0, 0, 0, 0, 0, 0, 0, 0, 0, 0, 0, 0, 0, 0, 0, 0, 0, 0, 0, 0, 0, 0, 0, 0, 0, 0, 0, 0, 0, 0, 0, 0, 0, 0, 0, 1, 0, 0, 0, 0, 0, 0, 1610612745],
         "height":9,
         "name":"ground",
         "offsetx":248,
         "offsety":-424,
         "opacity":1,
         "type":"tilelayer",
         "visible":true,
         "width":300,
         "x":0,
         "y":0
        }, 
        {
         "draworder":"topdown",
         "name":"env_forward",
         "objects":[
                {
                 "gid":38,
                 "height":201,
                 "id":2,
                 "name":"igloo1",
                 "properties":
                    {
                     "height":201,
                     "width":511
                    },
                 "propertytypes":
                    {
                     "height":"float",
                     "width":"float"
                    },
                 "rotation":0,
                 "type":"igloo",
                 "visible":true,
                 "width":511,
                 "x":503,
                 "y":1043
                }, 
                {
                 "gid":47,
                 "height":202.242,
                 "id":31,
                 "name":"stone1",
                 "properties":
                    {
                     "height":202.24,
                     "width":321.51
                    },
                 "propertytypes":
                    {
                     "height":"float",
                     "width":"float"
                    },
                 "rotation":0,
                 "type":"stone",
                 "visible":true,
                 "width":321.514,
                 "x":8342.27,
                 "y":777.667
                }, 
                {
                 "gid":43,
                 "height":249.455,
                 "id":34,
                 "name":"tree_1_4",
                 "properties":
                    {
                     "height":249.46,
                     "width":317.76
                    },
                 "propertytypes":
                    {
                     "height":"float",
                     "width":"float"
                    },
                 "rotation":0,
                 "type":"tree_1",
                 "visible":true,
                 "width":317.758,
                 "x":16090.6,
                 "y":656
                }, 
                {
                 "gid":43,
                 "height":249.455,
                 "id":35,
                 "name":"tree_1_2",
                 "properties":
                    {
                     "height":249.46,
                     "width":317.76
                    },
                 "propertytypes":
                    {
                     "height":"float",
                     "width":"float"
                    },
                 "rotation":0,
                 "type":"tree_1",
                 "visible":true,
                 "width":317.758,
                 "x":15727.9,
                 "y":655
                }, 
                {
                 "gid":40,
                 "height":131.483,
                 "id":51,
                 "name":"sign_2_2",
                 "properties":
                    {
                     "height":131.48,
                     "width":123
                    },
                 "propertytypes":
                    {
                     "height":"float",
                     "width":"float"
                    },
                 "rotation":0,
                 "type":"sign_2",
                 "visible":true,
                 "width":123,
                 "x":36763.5,
                 "y":519.925
                }, 
                {
                 "gid":38,
                 "height":201,
                 "id":76,
                 "name":"igloo3",
                 "properties":
                    {
                     "height":201,
                     "width":511
                    },
                 "propertytypes":
                    {
                     "height":"float",
                     "width":"float"
                    },
                 "rotation":0,
                 "type":"igloo",
                 "visible":true,
                 "width":511,
                 "x":34472.5,
                 "y":775.5
                }, 
                {
                 "gid":37,
                 "height":101,
                 "id":79,
                 "name":"icebox10",
                 "properties":
                    {
                     "height":101,
                     "width":101
                    },
                 "propertytypes":
                    {
                     "height":"float",
                     "width":"float"
                    },
                 "rotation":0,
                 "type":"icebox",
                 "visible":true,
                 "width":101,
                 "x":6378.5,
                 "y":363.5
                }, 
                {
                 "gid":37,
                 "height":101,
                 "id":80,
                 "name":"icebox11",
                 "properties":
                    {
                     "height":101,
                     "width":101
                    },
                 "propertytypes":
                    {
                     "height":"float",
                     "width":"float"
                    },
                 "rotation":0,
                 "type":"icebox",
                 "visible":true,
                 "width":101,
                 "x":6477.5,
                 "y":362.5
                }, 
                {
                 "gid":37,
                 "height":101,
                 "id":81,
                 "name":"icebox12",
                 "properties":
                    {
                     "height":101,
                     "width":101
                    },
                 "propertytypes":
                    {
                     "height":"float",
                     "width":"float"
                    },
                 "rotation":0,
                 "type":"icebox",
                 "visible":true,
                 "width":101,
                 "x":6577.5,
                 "y":363.5
                }],
         "offsetx":256,
         "offsety":-432,
         "opacity":1,
         "type":"objectgroup",
         "visible":false,
         "x":0,
         "y":0
        }, 
        {
         "data":[0, 0, 0, 0, 0, 0, 0, 0, 0, 0, 0, 0, 0, 0, 0, 0, 0, 0, 0, 0, 0, 0, 0, 0, 0, 0, 0, 0, 0, 0, 0, 0, 0, 0, 0, 0, 0, 0, 0, 0, 0, 0, 0, 0, 0, 0, 0, 0, 0, 0, 0, 0, 0, 0, 0, 0, 0, 0, 0, 0, 0, 0, 0, 0, 0, 0, 0, 0, 0, 0, 0, 0, 0, 0, 0, 0, 0, 0, 0, 0, 0, 0, 0, 0, 0, 0, 0, 0, 0, 0, 0, 0, 0, 0, 0, 0, 0, 0, 0, 0, 0, 0, 0, 0, 0, 0, 0, 0, 0, 0, 0, 0, 0, 0, 0, 0, 0, 0, 0, 0, 0, 0, 0, 0, 0, 0, 0, 0, 0, 0, 0, 0, 0, 0, 0, 0, 0, 0, 0, 0, 0, 0, 0, 0, 0, 0, 0, 0, 0, 0, 0, 0, 0, 0, 0, 0, 0, 0, 0, 0, 0, 0, 0, 0, 0, 0, 0, 0, 0, 0, 0, 0, 0, 0, 0, 0, 0, 0, 0, 0, 0, 0, 0, 0, 0, 0, 0, 0, 0, 0, 0, 0, 0, 0, 0, 0, 0, 0, 0, 0, 0, 0, 0, 0, 0, 0, 0, 0, 0, 0, 0, 0, 0, 0, 0, 0, 0, 0, 0, 0, 0, 0, 0, 0, 0, 0, 0, 0, 0, 0, 0, 0, 0, 0, 0, 0, 0, 0, 0, 0, 0, 0, 0, 0, 0, 0, 0, 0, 0, 0, 0, 0, 0, 0, 0, 0, 0, 0, 0, 0, 0, 0, 0, 0, 0, 0, 0, 0, 0, 0, 0, 0, 0, 0, 0, 0, 0, 0, 0, 0, 0, 0, 0, 0, 0, 0, 0, 0, 0, 0, 0, 0, 0, 0, 0, 0, 0, 0, 0, 0, 0, 0, 0, 0, 0, 0, 0, 0, 0, 0, 0, 0, 0, 0, 0, 0, 0, 0, 0, 0, 0, 0, 0, 0, 0, 0, 0, 0, 0, 0, 0, 0, 0, 0, 0, 0, 0, 0, 0, 0, 0, 0, 0, 0, 0, 0, 0, 0, 0, 0, 0, 0, 0, 0, 0, 0, 0, 0, 0, 0, 0, 0, 0, 0, 0, 0, 0, 0, 0, 0, 0, 0, 0, 0, 0, 0, 0, 0, 0, 0, 0, 0, 0, 0, 0, 0, 0, 0, 0, 0, 0, 0, 0, 0, 0, 0, 0, 0, 0, 0, 0, 0, 0, 0, 0, 0, 0, 0, 0, 0, 0, 0, 0, 0, 0, 0, 0, 0, 0, 0, 0, 0, 0, 0, 0, 0, 0, 0, 0, 0, 0, 0, 0, 0, 0, 0, 0, 0, 0, 0, 0, 0, 0, 0, 0, 0, 0, 0, 0, 0, 0, 0, 0, 0, 0, 0, 0, 0, 0, 0, 0, 0, 0, 0, 0, 0, 0, 0, 0, 0, 0, 0, 0, 0, 0, 0, 0, 0, 0, 0, 0, 0, 0, 0, 0, 0, 0, 0, 0, 0, 0, 0, 0, 0, 0, 0, 0, 0, 0, 0, 0, 0, 0, 0, 0, 0, 0, 0, 0, 0, 0, 0, 0, 0, 0, 0, 0, 0, 0, 0, 0, 0, 0, 0, 0, 0, 0, 0, 0, 0, 0, 0, 0, 0, 0, 0, 0, 0, 0, 0, 0, 0, 0, 0, 0, 0, 0, 0, 0, 0, 0, 0, 0, 0, 0, 0, 0, 0, 0, 0, 0, 0, 0, 0, 0, 0, 0, 0, 0, 0, 0, 0, 0, 0, 0, 0, 0, 0, 0, 0, 0, 0, 0, 0, 0, 0, 0, 0, 0, 0, 0, 0, 0, 0, 0, 0, 0, 0, 0, 0, 0, 0, 0, 0, 0, 0, 0, 0, 0, 0, 0, 0, 0, 0, 0, 0, 0, 0, 0, 0, 0, 0, 0, 0, 0, 0, 0, 0, 0, 0, 0, 0, 0, 0, 0, 0, 0, 0, 0, 0, 0, 0, 0, 0, 0, 0, 0, 0, 0, 0, 0, 0, 0, 0, 0, 0, 0, 0, 0, 0, 0, 0, 0, 0, 0, 0, 0, 0, 0, 0, 0, 0, 0, 0, 0, 0, 0, 0, 0, 0, 0, 0, 0, 0, 0, 0, 0, 0, 0, 0, 0, 0, 0, 0, 0, 0, 0, 0, 0, 0, 0, 0, 0, 0, 0, 0, 0, 0, 0, 0, 0, 0, 0, 0, 0, 0, 0, 0, 0, 0, 0, 0, 0, 0, 0, 0, 0, 0, 0, 0, 0, 0, 0, 0, 0, 0, 0, 0, 0, 0, 0, 0, 0, 0, 0, 0, 0, 0, 0, 0, 0, 0, 0, 0, 0, 0, 0, 0, 0, 0, 0, 0, 0, 0, 0, 0, 0, 0, 0, 0, 0, 0, 0, 0, 0, 0, 0, 0, 0, 0, 0, 0, 0, 0, 0, 0, 0, 0, 0, 0, 0, 0, 0, 0, 0, 0, 0, 0, 0, 0, 0, 0, 0, 0, 0, 0, 0, 0, 0, 0, 0, 0, 0, 0, 0, 0, 0, 0, 0, 0, 0, 0, 0, 0, 0, 0, 0, 0, 0, 0, 0, 0, 0, 0, 0, 0, 0, 0, 0, 0, 0, 0, 0, 0, 0, 0, 0, 0, 0, 0, 0, 0, 0, 0, 0, 0, 0, 0, 0, 0, 0, 0, 0, 0, 0, 0, 0, 0, 0, 0, 0, 0, 0, 0, 0, 0, 0, 0, 0, 0, 0, 0, 0, 0, 0, 0, 0, 0, 0, 0, 0, 0, 0, 0, 0, 0, 0, 0, 0, 0, 0, 0, 0, 0, 0, 0, 0, 0, 0, 0, 0, 0, 0, 0, 0, 0, 0, 0, 0, 0, 0, 0, 0, 0, 0, 0, 0, 0, 0, 0, 0, 0, 0, 0, 0, 0, 0, 0, 0, 0, 0, 0, 0, 0, 0, 0, 0, 0, 3, 3, 3, 3, 3, 3, 0, 0, 0, 0, 0, 0, 0, 0, 0, 0, 0, 0, 0, 0, 0, 0, 0, 0, 0, 0, 0, 0, 0, 0, 0, 0, 0, 0, 0, 0, 0, 0, 0, 0, 0, 0, 0, 0, 0, 0, 0, 0, 0, 0, 0, 0, 0, 0, 0, 0, 0, 0, 0, 0, 0, 0, 0, 0, 0, 0, 0, 0, 0, 0, 0, 0, 0, 0, 0, 0, 0, 0, 0, 0, 0, 0, 0, 0, 0, 0, 0, 0, 0, 0, 0, 0, 0, 0, 0, 0, 0, 0, 0, 0, 0, 0, 0, 0, 0, 0, 0, 0, 0, 0, 0, 0, 0, 0, 0, 0, 0, 0, 0, 0, 0, 0, 0, 0, 0, 0, 0, 0, 0, 0, 0, 0, 0, 0, 0, 0, 0, 0, 0, 0, 0, 0, 0, 0, 0, 0, 0, 0, 0, 0, 0, 0, 0, 0, 0, 0, 0, 0, 0, 0, 0, 0, 0, 0, 0, 0, 0, 0, 0, 0, 0, 0, 0, 0, 0, 0, 0, 0, 0, 0, 0, 0, 0, 0, 0, 0, 0, 0, 0, 0, 0, 0, 0, 0, 0, 0, 0, 0, 0, 0, 0, 0, 0, 0, 0, 0, 0, 0, 0, 0, 0, 0, 0, 0, 0, 0, 0, 0, 0, 0, 0, 0, 0, 0, 0, 0, 0, 0, 0, 0, 0, 0, 0, 0, 0, 0, 0, 0, 0, 0, 0, 0, 0, 0, 0, 0, 0, 0, 0, 0, 0, 0, 0, 0, 0, 0, 0, 0, 0, 0, 0, 0, 0, 0, 0, 0, 0, 0, 0, 0, 0, 0, 0, 0, 0, 0, 0, 0, 0, 0, 0, 0, 0, 0, 0, 0, 0, 0, 0, 0, 0, 0, 0, 0, 0, 0, 0, 0, 0, 0, 10, 10, 10, 10, 10, 10, 0, 0, 0, 0, 0, 0, 0, 0, 0, 0, 0, 0, 0, 0, 0, 0, 0, 0, 0, 0, 0, 0, 0, 0, 0, 0, 0, 0, 0, 0, 0, 0, 0, 0, 0, 0, 0, 0, 0, 0, 0, 0, 0, 0, 0, 0, 0, 0, 0, 0, 0, 0, 0, 0, 0, 0, 0, 0, 0, 0, 0, 0, 0, 0, 0, 0, 0, 0, 0, 0, 0, 0, 0, 0, 0, 0, 0, 0, 0, 0, 0, 0, 0, 0, 0, 0, 0, 0, 0, 0, 0, 0, 0, 0, 0, 0, 0, 0, 0, 0, 0, 0, 0, 0, 0, 0, 0, 0, 0, 0, 0, 0, 0, 0, 0, 0, 0, 0, 0, 0, 0, 0, 0, 0, 0, 0, 0, 0, 0, 0, 0, 0, 0, 0, 0, 0, 0, 0, 0, 0, 0, 0, 0, 0, 0, 0, 0, 0, 0, 0, 0, 0, 0, 0, 0, 0, 0, 0, 0, 0, 0, 0, 0, 0, 0, 0, 0, 0, 0, 0, 0, 0, 0, 0, 0, 0, 0, 0, 0, 0, 0, 0, 0, 0, 0, 0, 0, 0, 0, 0, 0, 0, 0, 0, 0, 0, 0, 0, 0, 0, 0, 0, 0, 0, 0, 0, 0, 0, 0, 0, 0, 0, 0, 0, 0, 0, 0, 0, 0, 0, 0, 0, 0, 0, 0, 0, 0, 0, 0, 0, 0, 0, 0, 0, 0, 0, 0, 0, 0, 0, 0, 0, 0, 0, 0, 0, 0, 0, 0, 0, 0, 0, 0, 0, 0, 0, 0, 0, 0, 0, 0, 0, 0, 0, 0, 0, 0, 0, 0, 0, 0, 0, 0, 0, 0, 0, 0, 0, 0, 0, 0, 0, 0, 0, 0, 0, 0, 0, 0, 0, 0, 0, 0, 0, 0, 0, 0, 0, 0, 0, 0, 0, 0, 0, 0, 0, 0, 0, 0, 0, 0, 0, 0, 0, 0, 0, 0, 0, 0, 0, 0, 0, 0, 0, 0, 0, 0, 0, 0, 0, 0, 0, 0, 0, 0, 0, 0, 0, 0, 0, 0, 0, 0, 0, 0, 0, 0, 0, 0, 0, 0, 0, 0, 0, 0, 0, 0, 0, 0, 0, 0, 0, 0, 0, 0, 0, 0, 0, 0, 0, 0, 0, 0, 0, 0, 0, 0, 0, 0, 0, 0, 0, 0, 0, 0, 0, 0, 0, 0, 0, 0, 0, 0, 0, 0, 0, 0, 0, 0, 0, 0, 0, 0, 0, 0, 0, 0, 0, 0, 0, 0, 0, 0, 0, 0, 0, 0, 0, 0, 0, 0, 0, 0, 0, 0, 0, 0, 0, 0, 0, 0, 0, 0, 0, 0, 0, 0, 0, 0, 0, 0, 0, 0, 0, 0, 0, 0, 0, 0, 0, 0, 0, 0, 0, 0, 0, 0, 0, 0, 0, 0, 0, 0, 0, 0, 0, 0, 0, 0, 0, 0, 0, 0, 0, 0, 0, 0, 0, 0, 0, 0, 0, 0, 0, 0, 0, 0, 0, 0, 0, 0, 0, 0, 0, 0, 0, 0, 0, 0, 0, 0, 0, 0, 0, 0, 0, 0, 0, 0, 0, 0, 0, 0, 0, 0, 0, 0, 0, 0, 0, 0, 0, 0, 0, 0, 0, 0, 0, 0, 0, 0, 0, 0, 0, 0, 0, 0, 0, 0, 0, 0, 0, 0, 0, 0, 0, 0, 0, 0, 0, 0, 0, 0, 0, 0, 0, 0, 0, 0, 0, 0, 0, 0, 0, 0, 0, 0, 0, 0, 0, 0, 0, 0, 0, 0, 0, 0, 0, 0, 0, 0, 0, 0, 0, 0, 0, 0, 0, 0, 0, 0, 0, 0, 0, 0, 0, 0, 0, 0, 0, 0, 0, 0, 0, 0, 0, 0, 0, 0, 0, 0, 0, 0, 0, 0, 0, 0, 0, 0, 0, 0, 0, 0, 0, 0, 0, 0, 0, 0, 0, 0, 0, 0, 0, 0, 0, 0, 0, 0, 0, 0, 0, 0, 0, 0, 0, 0, 0, 0, 0, 0, 0, 0, 0, 0, 0, 0, 0, 0, 0, 0, 0, 0, 0, 0, 0, 0, 0, 0, 0, 0, 0, 0, 0, 0, 0, 0, 0, 0, 0, 0, 0, 0, 0, 0, 0, 0, 0, 0, 0, 0, 0, 0, 0, 0, 0, 0, 0, 0, 0, 0, 0, 0, 0, 0, 0, 0, 0, 0, 0, 0, 0, 0, 0, 0, 0, 0, 0, 0, 0, 0, 0, 0, 0, 0, 0, 0, 0, 0, 0, 0, 0, 0, 0, 0, 0, 0, 0, 0, 0, 0, 0, 0, 0, 0, 0, 0, 0, 0, 0, 0, 0, 0, 0, 0, 0, 0, 0, 0, 0, 0, 0, 0, 0, 0, 0, 0, 0, 0, 0, 0, 0, 0, 0, 0, 0, 0, 0, 0, 0, 0, 0, 0, 0, 0, 0, 0, 0, 0, 0, 0, 0, 0, 0, 0, 0, 0, 0, 0, 0, 0, 0, 0, 0, 0, 0, 0, 0, 0, 0, 0, 0, 0, 0, 0, 0, 0, 0, 0, 0, 0, 0, 0, 0, 0, 0, 0, 0, 0, 0, 0, 0, 0, 0, 0, 0, 0, 0, 0, 0, 0, 0, 0, 0, 0, 0, 0, 0, 0, 0, 0, 0, 0, 0, 0, 0, 0, 0, 0, 0, 0, 0, 0, 0, 0, 0, 0, 0, 0, 0, 0, 0, 0, 0, 0, 0, 0, 0, 0, 0, 0, 0, 0, 0, 0, 0, 0, 0, 0, 0, 0, 0, 0, 0, 0, 0, 0, 0, 0, 0, 0, 0, 0, 0, 0, 0, 0, 0, 0, 0, 0, 0, 0, 0, 0, 0, 0, 0, 0, 0, 0, 0, 0, 0, 0, 0, 0, 0, 0, 0, 0, 0, 0, 0, 0, 0, 0, 0, 0, 0, 0, 0, 0, 0, 0, 0, 0, 0, 0, 0, 0, 0, 0, 0, 0, 0, 0, 0, 0, 0, 0, 0, 0, 0, 0, 0, 0, 0, 0, 0, 0, 0, 0, 0, 0, 0, 0, 0, 0, 0, 0, 0, 0, 0, 0, 0, 0, 0, 0, 0, 0, 0, 0, 0, 0, 0, 0, 0, 0, 0, 0, 0, 0, 0, 0, 0, 0, 0, 0, 0, 0, 0, 0, 0, 0, 0, 0, 0, 0, 0, 0, 0, 0, 0, 0, 0, 0, 0, 0, 0, 0, 0, 0, 0, 0, 0, 0, 0, 0, 0, 0, 0, 0, 0, 0, 0, 0, 0, 0, 0, 0, 0, 0, 0, 0, 0, 0, 0, 0, 0, 0, 0, 0, 0, 0, 0, 0, 0, 0, 0, 0, 0, 0, 0, 0, 0, 0, 0, 0, 0, 0, 0, 0, 0, 0, 0, 0, 0, 0, 0, 0, 0, 0, 0, 0, 0, 0, 0, 0, 0, 0, 0, 0, 0, 0, 0, 0, 0, 0, 0, 0, 0, 0, 0, 0, 0, 0, 0, 0, 0, 0, 0, 0, 0, 0, 0, 0, 0, 0, 0, 0, 0, 0, 0, 0, 0, 0, 0, 0, 0, 0, 0, 0, 0, 0, 0, 0, 0, 0, 0, 0, 0, 0, 0, 3, 3, 3, 3, 3, 3, 3, 3, 3, 3, 3, 3, 3, 3, 3, 3, 3, 3, 0, 0, 0, 3, 3, 0, 0, 3, 0, 0, 0, 3, 3, 0, 0, 3, 3, 0, 0, 0, 0, 0, 0, 0, 0, 0, 3, 3, 3, 0, 0, 0, 0, 0, 0, 0, 0, 0, 3, 0, 0, 0, 3, 3, 0, 0, 0, 0, 0, 0, 0, 0, 3, 3, 3, 3, 3, 3, 3, 3, 3, 3, 3, 3, 3, 3, 3, 3, 3, 3, 0, 3, 3, 0, 0, 0, 3, 3, 0, 0, 3, 0, 0, 3, 0, 0, 3, 3, 3, 3, 3, 3, 3, 3, 3, 3, 3, 0, 0, 0, 0, 0, 3, 3, 3, 3, 3, 3, 3, 3, 0, 0, 0, 3, 3, 3, 3, 3, 3, 3, 3, 3, 3, 3, 3, 3, 3, 3, 3, 3, 0, 0, 0, 0, 0, 0, 0, 0, 0, 0, 0, 3, 3, 0, 0, 0, 3, 3, 0, 0, 0, 3, 3, 0, 3, 3, 0, 0, 0, 3, 0, 0, 3, 3, 3, 3, 3, 3, 3, 3, 3, 3, 3, 0, 0, 0, 3, 0, 3, 0, 0, 3, 3, 0, 0, 0, 3, 0, 3, 0, 0, 0, 3, 0, 3, 0, 0, 0, 3, 0, 0, 0, 3, 0, 3, 0, 3, 0, 0, 0, 3, 0, 0, 0, 0, 0, 0, 3, 3, 3, 3, 3, 3, 3, 3, 3, 3, 3, 3, 3, 3, 3, 3, 3, 3, 3, 3, 3, 3, 3, 3, 3, 3, 3, 3, 3, 3, 3, 3, 3, 3, 3, 3, 3, 3, 3, 3, 3, 3, 3, 3, 3, 3, 3, 3, 3, 0, 0, 0, 0, 0, 0, 0, 0],
         "height":9,
         "name":"water",
         "offsetx":245.454545454545,
         "offsety":-424.242424242424,
         "opacity":1,
         "type":"tilelayer",
         "visible":false,
         "width":300,
         "x":0,
         "y":0
        }],
 "nextobjectid":82,
 "orientation":"orthogonal",
 "renderorder":"left-down",
 "tiledversion":"2017.07.17",
 "tileheight":128,
 "tilesets":[
        {
         "columns":5,
         "firstgid":1,
         "image":"winter.png",
         "imageheight":640,
         "imagewidth":640,
         "margin":0,
         "name":"winter",
         "spacing":0,
         "tilecount":25,
         "tileheight":128,
         "tilewidth":128
        }, 
        {
         "columns":0,
         "firstgid":26,
         "grid":
            {
             "height":1,
             "orientation":"orthogonal",
             "width":1
            },
         "margin":0,
         "name":"obj_winter",
         "spacing":0,
         "tilecount":8,
         "tileheight":280,
         "tiles":
            {
             "11":
                {
                 "image":"icebox.png",
                 "imageheight":101,
                 "imagewidth":101
                },
             "12":
                {
                 "image":"igloo.png",
                 "imageheight":201,
                 "imagewidth":511
                },
             "13":
                {
                 "image":"Sign_1.png",
                 "imageheight":94,
                 "imagewidth":87
                },
             "14":
                {
                 "image":"sign_2.png",
                 "imageheight":93,
                 "imagewidth":87
                },
             "17":
                {
                 "image":"tree_1.png",
                 "imageheight":280,
                 "imagewidth":364
                },
             "18":
                {
                 "image":"tree_2.png",
                 "imageheight":280,
                 "imagewidth":228
                },
             "20":
                {
                 "image":"snowman.png",
                 "imageheight":210,
                 "imagewidth":193
                },
             "21":
                {
                 "image":"stone.png",
                 "imageheight":78,
                 "imagewidth":124
                }
            },
         "tilewidth":511
        }, 
        {
         "columns":0,
         "firstgid":48,
         "grid":
            {
             "height":1,
             "orientation":"orthogonal",
             "width":1
            },
         "margin":0,
         "name":"box_winter",
         "spacing":0,
         "tilecount":1,
         "tileheight":101,
         "tiles":
            {
             "0":
                {
                 "image":"crate.png",
                 "imageheight":101,
                 "imagewidth":101
                }
            },
         "tilewidth":101
        }, 
        {
         "columns":0,
         "firstgid":49,
         "grid":
            {
             "height":1,
             "orientation":"orthogonal",
             "width":1
            },
         "margin":0,
         "name":"trap_winter",
         "spacing":0,
         "tilecount":1,
         "tileheight":78,
         "tiles":
            {
             "0":
                {
                 "image":"crystal.png",
                 "imageheight":78,
                 "imagewidth":97
                }
            },
         "tilewidth":97
        }],
 "tilewidth":128,
 "type":"map",
 "version":1,
 "width":300
}